garf/community/google/analytics/__init__.py
garf/community/google/analytics/api_clients.py
garf/community/google/analytics/query_editor.py
garf/community/google/analytics/report_fetcher.py
garf_google_analytics/__init__.py
garf_google_analytics/api_clients.py
garf_google_analytics/query_editor.py
garf_google_analytics/report_fetcher.py
garf_google_analytics-1.0.0.dist-info/METADATA
garf_google_analytics-1.0.0.dist-info/WHEEL
garf_google_analytics-1.0.0.dist-info/entry_points.txt
garf_google_analytics-1.0.0.dist-info/top_level.txt
garf_google_analytics-1.0.0.dist-info/RECORD
