Metadata-Version: 2.4
Name: garf-google-analytics
Version: 1.0.0
Summary: Garf implementation for Google Analytics API
Author-email: "Google Inc. (gTech gPS CSE team)" <no-reply@google.com>
License: Apache 2.0
Classifier: Development Status :: 2 - Pre-Alpha
Classifier: Programming Language :: Python
Requires-Python: >=3.8
Requires-Dist: garf-core
Requires-Dist: garf-io
Requires-Dist: google-analytics-data
